MANIFEST.in
README.txt
setup.py
HTML_as_programming_language.egg-info/PKG-INFO
HTML_as_programming_language.egg-info/SOURCES.txt
HTML_as_programming_language.egg-info/dependency_links.txt
HTML_as_programming_language.egg-info/entry_points.txt
HTML_as_programming_language.egg-info/requires.txt
HTML_as_programming_language.egg-info/top_level.txt
htmlc/__init__.py
htmlc/c_linker.py
htmlc/code_range.py
htmlc/compiler.py
htmlc/diagnostics.py
htmlc/html_parser.py
htmlc/json_rpc.py
htmlc/lang_server.py
htmlc/lexer.py
htmlc/linker.py
htmlc/mapped_c_string.py
htmlc/utils.py
htmlc/data/c_code/boolean.h
htmlc/data/c_code/avr/digital.c
htmlc/data/c_code/avr/atmega328p/serial.c
htmlc/elements/__init__.py
htmlc/elements/assembly.py
htmlc/elements/assign.py
htmlc/elements/boolean_elements.py
htmlc/elements/c.py
htmlc/elements/comment.py
htmlc/elements/element.py
htmlc/elements/expression.py
htmlc/elements/function.py
htmlc/elements/function_call.py
htmlc/elements/infinity.py
htmlc/elements/link.py
htmlc/elements/loop.py
htmlc/elements/return_element.py
htmlc/elements/rise_and_fall.py
htmlc/elements/var_and_const.py
htmlc/elements/what_is.py
htmlc/elements/avr/__init__.py
htmlc/elements/avr/atmega328p/__init__.py
htmlc/elements/avr/atmega328p/serial_begin.py
htmlc/elements/avr/atmega328p/serial_receive.py
htmlc/elements/avr/atmega328p/serial_transmit.py
htmlc/elements/avr/pin_elements/__init__.py
htmlc/elements/avr/pin_elements/digital_read.py
htmlc/elements/avr/pin_elements/digital_write.py
htmlc/elements/avr/pin_elements/pin.py
htmlc/elements/avr/pin_elements/pin_mode.py
htmlc/elements/pile_elements/__init__.py
htmlc/elements/pile_elements/have.py
htmlc/elements/pile_elements/pile.py
htmlc/elements/pile_elements/pile_action.py
htmlc/elements/pile_elements/upgrade.py
htmlc/gcc/__init__.py
htmlc/gcc/avr.py
htmlc/gcc/gcc.py