Metadata-Version: 1.0
Name: HTML-as-programming-language
Version: 0.1.21
Summary: (WIP) Write HTML-code that compiles to C
Home-page: https://github.com/HTML-as-programming-language/HTML-as-programming-language
Author: hilkojj
Author-email: hilkojj@outlook.com
License: UNKNOWN
Platform: UNKNOWN
